{"cameraMode":{"drawMode":0,"name":"Shaded","section":"Shading Mode"},"sceneLighting":true,"audioPlay":false,"sceneViewState":{"showFog":true,"showMaterialUpdate":false,"showSkybox":true,"showFlares":true,"showImageEffects":true,"showParticleSystems":true},"in2DMode":false,"pivot":{"x":63.78297424316406,"y":14.000503540039063,"z":1.7380409240722657},"rotation":{"x":0.21015000343322755,"y":0.7885189652442932,"z":-0.3820936381816864,"w":0.4336809515953064},"size":134.0997314453125,"orthographic":false}